myfirstmodelcsc/First_Test.py
myfirstmodelcsc/__init__.py
myfirstmodelcsc-1.0.dist-info/METADATA
myfirstmodelcsc-1.0.dist-info/WHEEL
myfirstmodelcsc-1.0.dist-info/top_level.txt
myfirstmodelcsc-1.0.dist-info/RECORD
