Metadata-Version: 2.1
Name: myfirstmodelcsc
Version: 1.0
Summary: A  module for test
Home-page: https://github.com/hustcsc?tab=projects
Author: CSC_HUST
Author-email: zzucsc@163.com
License: MIT
Requires: numpy
